environparse/__init__.py
environparse/examples/__init__.py
environparse/examples/httpserver.py
environparse/locale/zh_CN/LC_MESSAGES/environparse.mo
environparse/locale/zh_HK/LC_MESSAGES/environparse.mo
environparse/locale/zh_SG/LC_MESSAGES/environparse.mo
environparse/locale/zh_TW/LC_MESSAGES/environparse.mo
environparse-0.2.0.post1.dist-info/LICENSE
environparse-0.2.0.post1.dist-info/METADATA
environparse-0.2.0.post1.dist-info/WHEEL
environparse-0.2.0.post1.dist-info/top_level.txt
environparse-0.2.0.post1.dist-info/RECORD
