Metadata-Version: 2.1
Name: environparse
Version: 0.2.0.post1
Summary: Environment variable parsing library.
License: 木兰宽松许可证， 第2版
Keywords: env,environ,environment,parse,parser,argparse,optparse,envparse
Classifier: Programming Language :: Python :: 3
Requires-Python: >=3.10
License-File: LICENSE
Requires-Dist: rich <14,>=13
Requires-Dist: attrs <24,>=23
